Metadata-Version: 1.0
Name: despik-package-v1
Version: 0.3
Summary: Some work with yfinance for self education
Home-page: UNKNOWN
Author: UNKNOWN
Author-email: artomonik@gmail.com
License: UNKNOWN
Platform: UNKNOWN
